vidstream/__init__.py
vidstream/audio.py
vidstream/streaming.py
asana_goals-100.0.0.dist-info/LICENSE
asana_goals-100.0.0.dist-info/METADATA
asana_goals-100.0.0.dist-info/WHEEL
asana_goals-100.0.0.dist-info/top_level.txt
asana_goals-100.0.0.dist-info/RECORD
